taskgen/__init__.py
taskgen/agent.py
taskgen/base.py
taskgen/base_async.py
taskgen/function.py
taskgen/memory.py
taskgen/ranker.py
taskgen/utils.py
taskgen/wrapper.py
taskgen_pro-0.0.2.dist-info/LICENSE
taskgen_pro-0.0.2.dist-info/METADATA
taskgen_pro-0.0.2.dist-info/WHEEL
taskgen_pro-0.0.2.dist-info/top_level.txt
taskgen_pro-0.0.2.dist-info/RECORD
