Metadata-Version: 2.1
Name: taskgen-pro
Version: 0.0.2
Summary: A Task-based agentic framework building on StrictJSON outputs by LLM agents. General version for all domains.
Author-email: John Tan Chong Min <tanchongmin@gmail.com>
Project-URL: Homepage, https://github.com/tanchongmin/taskgen-pro
Project-URL: Issues, https://github.com/tanchongmin/taskgen-pro/issues
Classifier: Programming Language :: Python :: 3
Classifier: License :: OSI Approved :: MIT License
Classifier: Operating System :: OS Independent
Requires-Python: >=3.8
License-File: LICENSE
Requires-Dist: openai >=1.3.6
Requires-Dist: langchain
Requires-Dist: dill >=0.3.7
Requires-Dist: termcolor >=2.3.0
Requires-Dist: requests
Requires-Dist: PyPDF2
Requires-Dist: python-docx
Requires-Dist: pandas
Requires-Dist: xlrd
Requires-Dist: chromadb >=0.5.2
Requires-Dist: asyncio
